autorunner/__init__.py
autorunner/cli.py
autorunner/client.py
autorunner/compat.py
autorunner/exceptions.py
autorunner/loader.py
autorunner/make.py
autorunner/models.py
autorunner/parser.py
autorunner/response.py
autorunner/runner.py
autorunner/scaffold.py
autorunner/testcase.py
autorunner/utils.py
autorunner/app/__init__.py
autorunner/app/main.py
autorunner/app/routers/__init__.py
autorunner/app/routers/debug.py
autorunner/app/routers/debugtalk.py
autorunner/app/routers/deps.py
autorunner/builtin/__init__.py
autorunner/builtin/comparators.py
autorunner/builtin/functions.py
autorunner/dbcore/__init__.py
autorunner/dbcore/engine.py
autorunner/ext/__init__.py
autorunner/ext/har2case/__init__.py
autorunner/ext/har2case/core.py
autorunner/ext/har2case/utils.py
autorunner/ext/locust/__init__.py
autorunner/ext/locust/locustfile.py
autorunner/ext/uploader/__init__.py
autorunner/uicore/__init__.py
autorunner/uicore/config.py
autorunner/uicore/driver.py
autorunner/uicore/element.py
autorunner/uicore/local.py
autorunner/uicore/locator.py
autorunner/uicore/screenshot.py
autorunner/uicore/uirunner.py
autorunner/uicore/web_action.py
examples/httpbin/__init__.py
examples/httpbin/basic_test.py
examples/httpbin/debugtalk.py
examples/httpbin/hooks_test.py
examples/httpbin/load_image_test.py
examples/httpbin/upload_test.py
examples/httpbin/validate_test.py
examples/postman_echo/__init__.py
examples/postman_echo/conftest.py
examples/postman_echo/debugtalk.py
examples/postman_echo/validate.py
examples/postman_echo/cookie_manipulation/__init__.py
examples/postman_echo/cookie_manipulation/hardcode_test.py
examples/postman_echo/cookie_manipulation/set_delete_cookies_test.py
examples/postman_echo/request_methods/__init__.py
examples/postman_echo/request_methods/conftest.py
examples/postman_echo/request_methods/hardcode_test.py
examples/postman_echo/request_methods/request_with_functions_test.py
examples/postman_echo/request_methods/request_with_parameters_test.py
autorunner2-1.0.0.dist-info/METADATA
autorunner2-1.0.0.dist-info/WHEEL
autorunner2-1.0.0.dist-info/entry_points.txt
autorunner2-1.0.0.dist-info/top_level.txt
autorunner2-1.0.0.dist-info/RECORD
